Workbook

Sheet Master Calculator
A1: Membership | B1: # of Contestents | C1: Entry Fee
A2: 0 | B2: 100 | C2: 150
D3: Gross Pot | E3: Processing Fees 4% | F3: Gross to Pay
D4: =B2*C2 -> 15000 | E4: =D4*4% -> 600 | F4: =D4-E4 -> 14400 | G4: Payback/Holdings
F5: PR HOLDING | G5: 0.5 | H5: =F4*G5 -> 7200
F6: RACERS POT | G6: 0.5 | H6: =F4*G6 -> 7200
G7: =SUM(G5:G6) -> 1 | H7: =SUM(H5:H6) -> 14400
B8: =F10 | C8: True Added $ | D8: Contestant payback + True Added $
B9: =H6 -> 7200 | C9: 0 | D9: =B9+C9 -> 7200 | G9: PR | H9: 0.5 | I9: =H9*H5 -> 3600
G10: Producer | H10: 0.5 | I10: =H10*H5 -> 3600
B11: D1 Added $ | C11: Contestent Payback - D1 Added $ | D11: # of Contestent Divisions | E11: Even Division Payouts | H11: =SUM(H9:H10) -> 1 | I11: =SUM(I9:I10) -> 7200
B12: 0 | C12: =D9-B12 -> 7200 | D12: 5 | E12: =C12/D12 -> 1440
G13: Sponsorship | H13: Difference | I13: PR NET
B14: ALPHA TEAM | G14: 0 | H14: =I10-G14 -> 3600 | I14: =IF(OR(I9<0, H14<0), SUM(I9,H14), I9) -> 3600
B15: =B12+E12 -> 1440 | C15: Payout | D15: TOTAL DIVISIONS PAYOUT (Color box should Match)
A16: Placings | B16: 91-120 | D16: =sum(C30,C48,C66,C84,C102) -> 7200 | I16: Producer NET
A17: 1 | B17: =IFERROR(HLOOKUP(B16,'Payout Schedule'!$B$1:$M$13,A17+1,0),"") -> 0.33 | C17: =IFERROR(B15*B17,"") -> 475.2 | I17: =IF(I10 > G14, I10, G14) -> 3600
A18: 2 | B18: =IFERROR(HLOOKUP(B16,'Payout Schedule'!$B$1:$M$13,A18+1,0),"") -> 0.23 | C18: =IFERROR(B15*B18,"") -> 331.2
A19: 3 | B19: =IFERROR(HLOOKUP(B16,'Payout Schedule'!$B$1:$M$13,A19+1,0),"") -> 0.17 | C19: =IFERROR(B15*B19,"") -> 244.8 | I19: PR Membership
A20: 4 | B20: =IFERROR(HLOOKUP(B16,'Payout Schedule'!$B$1:$M$13,A20+1,0),"") -> 0.12 | C20: =IFERROR(B15*B20,"") -> 172.8 | G20: Membership Sales | H20: Rebate | I20: =G21-I22 -> 0
A21: 5 | B21: =IFERROR(HLOOKUP(B16,'Payout Schedule'!$B$1:$M$13,A21+1,0),"") -> 0.09 | C21: =IFERROR(B15*B21,"") -> 129.6 | G21: =A2*B2 -> 0 | H21: 0 | I21: Producer Rebate
A22: 6 | B22: =IFERROR(HLOOKUP(B16,'Payout Schedule'!$B$1:$M$13,A22+1,0),"") -> 0.06 | C22: =IFERROR(B15*B22,"") -> 86.4 | I22: =B2*H21 -> 0
A23: 7 | B23: =IFERROR(HLOOKUP(B16,'Payout Schedule'!$B$1:$M$13,A23+1,0),"") | C23: =IFERROR(B15*B23,"") -> 0
A24: 8 | B24: =IFERROR(HLOOKUP(B16,'Payout Schedule'!$B$1:$M$13,A24+1,0),"") | C24: =IFERROR(B15*B24,"") -> 0 | E24: RACE SNAPSHOT
A25: 9 | B25: =IFERROR(HLOOKUP(B16,'Payout Schedule'!$B$1:$M$13,A25+1,0),"") | C25: =IFERROR(B15*B25,"") -> 0 | E25: CONTESTANTS | F25: =D9 -> 7200
A26: 10 | B26: =IFERROR(HLOOKUP(B16,'Payout Schedule'!$B$1:$M$13,A26+1,0),"") | C26: =IFERROR(B15*B26,"") -> 0 | E26: PROMOTER | F26: =I22+I17 -> 3600
A27: 11 | B27: =IFERROR(HLOOKUP(B16,'Payout Schedule'!$B$1:$M$13,A27+1,0),"") | C27: =IFERROR(B15*B27,"") -> 0 | E27: PEER RACING | F27: =I9+I20 -> 3600
A28: 12 | B28: =IFERROR(HLOOKUP(B16,'Payout Schedule'!$B$1:$M$13,A28+1,0),"") | C28: =IFERROR(B15*B28,"") -> 0
A30: Total | B30: =SUM(B17:B28) -> 1 | C30: =SUM(C17:C28) -> 1440
B32: BRAVO TEAM
B33: =IF(D12=1,0,IF(D12=2,E12,IF(D12=3,E12,IF(D12=4,E12,IF(D12=5,E12))))) -> 1440 | C33: Payout
A34: Placings | B34: 91-120
A35: 1 | B35: =IFERROR(HLOOKUP(B34,'Payout Schedule'!$B$1:$M$13,A35+1,0),"") -> 0.33 | C35: =IFERROR(B33*B35,"") -> 475.2
A36: 2 | B36: =IFERROR(HLOOKUP(B34,'Payout Schedule'!$B$1:$M$13,A36+1,0),"") -> 0.23 | C36: =IFERROR(B33*B36,"") -> 331.2
A37: 3 | B37: =IFERROR(HLOOKUP(B34,'Payout Schedule'!$B$1:$M$13,A37+1,0),"") -> 0.17 | C37: =IFERROR(B33*B37,"") -> 244.8
A38: 4 | B38: =IFERROR(HLOOKUP(B34,'Payout Schedule'!$B$1:$M$13,A38+1,0),"") -> 0.12 | C38: =IFERROR(B33*B38,"") -> 172.8
A39: 5 | B39: =IFERROR(HLOOKUP(B34,'Payout Schedule'!$B$1:$M$13,A39+1,0),"") -> 0.09 | C39: =IFERROR(B33*B39,"") -> 129.6
A40: 6 | B40: =IFERROR(HLOOKUP(B34,'Payout Schedule'!$B$1:$M$13,A40+1,0),"") -> 0.06 | C40: =IFERROR(B33*B40,"") -> 86.4
A41: 7 | B41: =IFERROR(HLOOKUP(B34,'Payout Schedule'!$B$1:$M$13,A41+1,0),"") | C41: =IFERROR(B33*B41,"") -> 0
A42: 8 | B42: =IFERROR(HLOOKUP(B34,'Payout Schedule'!$B$1:$M$13,A42+1,0),"") | C42: =IFERROR(B33*B42,"") -> 0
A43: 9 | B43: =IFERROR(HLOOKUP(B34,'Payout Schedule'!$B$1:$M$13,A43+1,0),"") | C43: =IFERROR(B33*B43,"") -> 0
A44: 10 | B44: =IFERROR(HLOOKUP(B34,'Payout Schedule'!$B$1:$M$13,A44+1,0),"") | C44: =IFERROR(B33*B44,"") -> 0
A45: 11 | B45: =IFERROR(HLOOKUP(B34,'Payout Schedule'!$B$1:$M$13,A45+1,0),"") | C45: =IFERROR(B33*B45,"") -> 0
A46: 12 | B46: =IFERROR(HLOOKUP(B34,'Payout Schedule'!$B$1:$M$13,A46+1,0),"") | C46: =IFERROR(B33*B46,"") -> 0
A48: Total | B48: =SUM(B35:B46) -> 1 | C48: =SUM(C35:C46) -> 1440
B50: CHARLIE TEAM
B51: =IF(D12=1,0,IF(D12=2,0,IF(D12=3,E12,IF(D12=4,E12,IF(D12=5,E12))))) -> 1440 | C51: Payout
A52: Placings | B52: 91-120
A53: 1 | B53: =IFERROR(HLOOKUP(B52,'Payout Schedule'!$B$1:$M$13,A53+1,0),"") -> 0.33 | C53: =IFERROR(B51*B53,"") -> 475.2
A54: 2 | B54: =IFERROR(HLOOKUP(B52,'Payout Schedule'!$B$1:$M$13,A54+1,0),"") -> 0.23 | C54: =IFERROR(B51*B54,"") -> 331.2
A55: 3 | B55: =IFERROR(HLOOKUP(B52,'Payout Schedule'!$B$1:$M$13,A55+1,0),"") -> 0.17 | C55: =IFERROR(B51*B55,"") -> 244.8
A56: 4 | B56: =IFERROR(HLOOKUP(B52,'Payout Schedule'!$B$1:$M$13,A56+1,0),"") -> 0.12 | C56: =IFERROR(B51*B56,"") -> 172.8
A57: 5 | B57: =IFERROR(HLOOKUP(B52,'Payout Schedule'!$B$1:$M$13,A57+1,0),"") -> 0.09 | C57: =IFERROR(B51*B57,"") -> 129.6
A58: 6 | B58: =IFERROR(HLOOKUP(B52,'Payout Schedule'!$B$1:$M$13,A58+1,0),"") -> 0.06 | C58: =IFERROR(B51*B58,"") -> 86.4
A59: 7 | B59: =IFERROR(HLOOKUP(B52,'Payout Schedule'!$B$1:$M$13,A59+1,0),"") | C59: =IFERROR(B51*B59,"") -> 0
A60: 8 | B60: =IFERROR(HLOOKUP(B52,'Payout Schedule'!$B$1:$M$13,A60+1,0),"") | C60: =IFERROR(B51*B60,"") -> 0
A61: 9 | B61: =IFERROR(HLOOKUP(B52,'Payout Schedule'!$B$1:$M$13,A61+1,0),"") | C61: =IFERROR(B51*B61,"") -> 0
A62: 10 | B62: =IFERROR(HLOOKUP(B52,'Payout Schedule'!$B$1:$M$13,A62+1,0),"") | C62: =IFERROR(B51*B62,"") -> 0
A63: 11 | B63: =IFERROR(HLOOKUP(B52,'Payout Schedule'!$B$1:$M$13,A63+1,0),"") | C63: =IFERROR(B51*B63,"") -> 0
A64: 12 | B64: =IFERROR(HLOOKUP(B52,'Payout Schedule'!$B$1:$M$13,A64+1,0),"") | C64: =IFERROR(B51*B64,"") -> 0
A66: Total | B66: =SUM(B53:B64) -> 1 | C66: =SUM(C53:C64) -> 1440
B68: DELTA TEAM
B69: =IF(D12=1,0,IF(D12=2,0,IF(D12=3,0,IF(D12=4,E12,IF(D12=5,E12))))) -> 1440 | C69: Payout
A70: Placings | B70: 91-120
A71: 1 | B71: =IFERROR(HLOOKUP(B70,'Payout Schedule'!$B$1:$M$13,A71+1,0),"") -> 0.33 | C71: =IFERROR(B69*B71,"") -> 475.2
A72: 2 | B72: =IFERROR(HLOOKUP(B70,'Payout Schedule'!$B$1:$M$13,A72+1,0),"") -> 0.23 | C72: =IFERROR(B69*B72,"") -> 331.2
A73: 3 | B73: =IFERROR(HLOOKUP(B70,'Payout Schedule'!$B$1:$M$13,A73+1,0),"") -> 0.17 | C73: =IFERROR(B69*B73,"") -> 244.8
A74: 4 | B74: =IFERROR(HLOOKUP(B70,'Payout Schedule'!$B$1:$M$13,A74+1,0),"") -> 0.12 | C74: =IFERROR(B69*B74,"") -> 172.8
A75: 5 | B75: =IFERROR(HLOOKUP(B70,'Payout Schedule'!$B$1:$M$13,A75+1,0),"") -> 0.09 | C75: =IFERROR(B69*B75,"") -> 129.6
A76: 6 | B76: =IFERROR(HLOOKUP(B70,'Payout Schedule'!$B$1:$M$13,A76+1,0),"") -> 0.06 | C76: =IFERROR(B69*B76,"") -> 86.4
A77: 7 | B77: =IFERROR(HLOOKUP(B70,'Payout Schedule'!$B$1:$M$13,A77+1,0),"") | C77: =IFERROR(B69*B77,"") -> 0
A78: 8 | B78: =IFERROR(HLOOKUP(B70,'Payout Schedule'!$B$1:$M$13,A78+1,0),"") | C78: =IFERROR(B69*B78,"") -> 0
A79: 9 | B79: =IFERROR(HLOOKUP(B70,'Payout Schedule'!$B$1:$M$13,A79+1,0),"") | C79: =IFERROR(B69*B79,"") -> 0
A80: 10 | B80: =IFERROR(HLOOKUP(B70,'Payout Schedule'!$B$1:$M$13,A80+1,0),"") | C80: =IFERROR(B69*B80,"") -> 0
A81: 11 | B81: =IFERROR(HLOOKUP(B70,'Payout Schedule'!$B$1:$M$13,A81+1,0),"") | C81: =IFERROR(B69*B81,"") -> 0
A82: 12 | B82: =IFERROR(HLOOKUP(B70,'Payout Schedule'!$B$1:$M$13,A82+1,0),"") | C82: =IFERROR(B69*B82,"") -> 0
A84: Total | B84: =SUM(B71:B82) -> 1 | C84: =SUM(C71:C82) -> 1440
B86: ECHO TEAM
B87: =IF(D12=1,0,IF(D12=2,0,IF(D12=3,0,IF(D12=4,0,IF(D12=5,E12))))) -> 1440 | C87: Payout
A88: Placings | B88: 91-120
A89: 1 | B89: =IFERROR(HLOOKUP(B88,'Payout Schedule'!$B$1:$M$13,A89+1,0),"") -> 0.33 | C89: =IFERROR(B87*B89,"") -> 475.2
A90: 2 | B90: =IFERROR(HLOOKUP(B88,'Payout Schedule'!$B$1:$M$13,A90+1,0),"") -> 0.23 | C90: =IFERROR(B87*B90,"") -> 331.2
A91: 3 | B91: =IFERROR(HLOOKUP(B88,'Payout Schedule'!$B$1:$M$13,A91+1,0),"") -> 0.17 | C91: =IFERROR(B87*B91,"") -> 244.8
A92: 4 | B92: =IFERROR(HLOOKUP(B88,'Payout Schedule'!$B$1:$M$13,A92+1,0),"") -> 0.12 | C92: =IFERROR(B87*B92,"") -> 172.8
A93: 5 | B93: =IFERROR(HLOOKUP(B88,'Payout Schedule'!$B$1:$M$13,A93+1,0),"") -> 0.09 | C93: =IFERROR(B87*B93,"") -> 129.6
A94: 6 | B94: =IFERROR(HLOOKUP(B88,'Payout Schedule'!$B$1:$M$13,A94+1,0),"") -> 0.06 | C94: =IFERROR(B87*B94,"") -> 86.4
A95: 7 | B95: =IFERROR(HLOOKUP(B88,'Payout Schedule'!$B$1:$M$13,A95+1,0),"") | C95: =IFERROR(B87*B95,"") -> 0
A96: 8 | B96: =IFERROR(HLOOKUP(B88,'Payout Schedule'!$B$1:$M$13,A96+1,0),"") | C96: =IFERROR(B87*B96,"") -> 0
A97: 9 | B97: =IFERROR(HLOOKUP(B88,'Payout Schedule'!$B$1:$M$13,A97+1,0),"") | C97: =IFERROR(B87*B97,"") -> 0
A98: 10 | B98: =IFERROR(HLOOKUP(B88,'Payout Schedule'!$B$1:$M$13,A98+1,0),"") | C98: =IFERROR(B87*B98,"") -> 0
A99: 11 | B99: =IFERROR(HLOOKUP(B88,'Payout Schedule'!$B$1:$M$13,A99+1,0),"") | C99: =IFERROR(B87*B99,"") -> 0
A100: 12 | B100: =IFERROR(HLOOKUP(B88,'Payout Schedule'!$B$1:$M$13,A100+1,0),"") | C100: =IFERROR(B87*B100,"") -> 0
A102: Total | B102: =SUM(B89:B100) -> 1 | C102: =SUM(C89:C100) -> 1440

Sheet sequiya 
A1: Membership | B1: # of Contestents | C1: Entry Fee
A2: 0 | B2: 200 | C2: 90
D3: Gross Pot | E3: Processing Fees 4% | F3: Gross to Pay
D4: =B2*C2 -> 18000 | E4: =D4*4% -> 720 | F4: =D4-E4 -> 17280 | G4: Payback/Holdings
F5: PR HOLDING | G5: 0.6 | H5: =F4*G5 -> 10368
F6: RACERS POT | G6: 0.4 | H6: =F4*G6 -> 6912
G7: =SUM(G5:G6) -> 1 | H7: =SUM(H5:H6) -> 17280
B8: =F10 | C8: True Added $ | D8: Contestant payback + True Added $
B9: =H6 -> 6912 | C9: 0 | D9: =B9+C9 -> 6912 | G9: PR | H9: 0.5 | I9: =H9*H5 -> 5184
G10: Producer | H10: 0.5 | I10: =H10*H5 -> 5184
B11: D1 Added $ | C11: Contestent Payback - D1 Added $ | D11: # of Contestent Divisions | E11: Even Division Payouts | H11: =SUM(H9:H10) -> 1 | I11: =SUM(I9:I10) -> 10368
B12: 1000 | C12: =D9-B12 -> 5912 | D12: 5 | E12: =C12/D12 -> 1182.4
G13: Sponsorship | H13: Difference | I13: PR NET
B14: ALPHA TEAM | G14: 0 | H14: =I10-G14 -> 5184 | I14: =IF(OR(I9<0, H14<0), SUM(I9,H14), I9) -> 5184
B15: =B12+E12 -> 2182.4 | C15: Payout | D15: TOTAL DIVISIONS PAYOUT (Color box should Match)
A16: Placings | B16: 61-90 | D16: =sum(C30,C48,C66,C84,C102) -> 6912 | I16: Producer NET
A17: 1 | B17: =IFERROR(HLOOKUP(B16,'Payout Schedule'!$B$1:$M$13,A17+1,0),"") -> 0.35 | C17: =IFERROR(B15*B17,"") -> 763.84 | I17: =IF(I10 > G14, I10, G14) -> 5184
A18: 2 | B18: =IFERROR(HLOOKUP(B16,'Payout Schedule'!$B$1:$M$13,A18+1,0),"") -> 0.25 | C18: =IFERROR(B15*B18,"") -> 545.6
A19: 3 | B19: =IFERROR(HLOOKUP(B16,'Payout Schedule'!$B$1:$M$13,A19+1,0),"") -> 0.19 | C19: =IFERROR(B15*B19,"") -> 414.656 | I19: PR Membership
A20: 4 | B20: =IFERROR(HLOOKUP(B16,'Payout Schedule'!$B$1:$M$13,A20+1,0),"") -> 0.14 | C20: =IFERROR(B15*B20,"") -> 305.536 | G20: Membership Sales | H20: Rebate | I20: =G21-I22 -> 0
A21: 5 | B21: =IFERROR(HLOOKUP(B16,'Payout Schedule'!$B$1:$M$13,A21+1,0),"") -> 0.07 | C21: =IFERROR(B15*B21,"") -> 152.768 | G21: =A2*B2 -> 0 | H21: 0 | I21: Producer Rebate
A22: 6 | B22: =IFERROR(HLOOKUP(B16,'Payout Schedule'!$B$1:$M$13,A22+1,0),"") | C22: =IFERROR(B15*B22,"") -> 0 | I22: =B2*H21 -> 0
A23: 7 | B23: =IFERROR(HLOOKUP(B16,'Payout Schedule'!$B$1:$M$13,A23+1,0),"") | C23: =IFERROR(B15*B23,"") -> 0
A24: 8 | B24: =IFERROR(HLOOKUP(B16,'Payout Schedule'!$B$1:$M$13,A24+1,0),"") | C24: =IFERROR(B15*B24,"") -> 0 | E24: RACE SNAPSHOT
A25: 9 | B25: =IFERROR(HLOOKUP(B16,'Payout Schedule'!$B$1:$M$13,A25+1,0),"") | C25: =IFERROR(B15*B25,"") -> 0 | E25: CONTESTANTS | F25: =D9 -> 6912
A26: 10 | B26: =IFERROR(HLOOKUP(B16,'Payout Schedule'!$B$1:$M$13,A26+1,0),"") | C26: =IFERROR(B15*B26,"") -> 0 | E26: PROMOTER | F26: =I22+I17 -> 5184
A27: 11 | B27: =IFERROR(HLOOKUP(B16,'Payout Schedule'!$B$1:$M$13,A27+1,0),"") | C27: =IFERROR(B15*B27,"") -> 0 | E27: PEER RACING | F27: =I9+I20 -> 5184
A28: 12 | B28: =IFERROR(HLOOKUP(B16,'Payout Schedule'!$B$1:$M$13,A28+1,0),"") | C28: =IFERROR(B15*B28,"") -> 0
A30: Total | B30: =SUM(B17:B28) -> 1 | C30: =SUM(C17:C28) -> 2182.4
B32: BRAVO TEAM
B33: =IF(D12=1,0,IF(D12=2,E12,IF(D12=3,E12,IF(D12=4,E12,IF(D12=5,E12))))) -> 1182.4 | C33: Payout
A34: Placings | B34: 61-90
A35: 1 | B35: =IFERROR(HLOOKUP(B34,'Payout Schedule'!$B$1:$M$13,A35+1,0),"") -> 0.35 | C35: =IFERROR(B33*B35,"") -> 413.84
A36: 2 | B36: =IFERROR(HLOOKUP(B34,'Payout Schedule'!$B$1:$M$13,A36+1,0),"") -> 0.25 | C36: =IFERROR(B33*B36,"") -> 295.6
A37: 3 | B37: =IFERROR(HLOOKUP(B34,'Payout Schedule'!$B$1:$M$13,A37+1,0),"") -> 0.19 | C37: =IFERROR(B33*B37,"") -> 224.656
A38: 4 | B38: =IFERROR(HLOOKUP(B34,'Payout Schedule'!$B$1:$M$13,A38+1,0),"") -> 0.14 | C38: =IFERROR(B33*B38,"") -> 165.536
A39: 5 | B39: =IFERROR(HLOOKUP(B34,'Payout Schedule'!$B$1:$M$13,A39+1,0),"") -> 0.07 | C39: =IFERROR(B33*B39,"") -> 82.768
A40: 6 | B40: =IFERROR(HLOOKUP(B34,'Payout Schedule'!$B$1:$M$13,A40+1,0),"") | C40: =IFERROR(B33*B40,"") -> 0
A41: 7 | B41: =IFERROR(HLOOKUP(B34,'Payout Schedule'!$B$1:$M$13,A41+1,0),"") | C41: =IFERROR(B33*B41,"") -> 0
A42: 8 | B42: =IFERROR(HLOOKUP(B34,'Payout Schedule'!$B$1:$M$13,A42+1,0),"") | C42: =IFERROR(B33*B42,"") -> 0
A43: 9 | B43: =IFERROR(HLOOKUP(B34,'Payout Schedule'!$B$1:$M$13,A43+1,0),"") | C43: =IFERROR(B33*B43,"") -> 0
A44: 10 | B44: =IFERROR(HLOOKUP(B34,'Payout Schedule'!$B$1:$M$13,A44+1,0),"") | C44: =IFERROR(B33*B44,"") -> 0
A45: 11 | B45: =IFERROR(HLOOKUP(B34,'Payout Schedule'!$B$1:$M$13,A45+1,0),"") | C45: =IFERROR(B33*B45,"") -> 0
A46: 12 | B46: =IFERROR(HLOOKUP(B34,'Payout Schedule'!$B$1:$M$13,A46+1,0),"") | C46: =IFERROR(B33*B46,"") -> 0
A48: Total | B48: =SUM(B35:B46) -> 1 | C48: =SUM(C35:C46) -> 1182.4
B50: CHARLIE TEAM
B51: =IF(D12=1,0,IF(D12=2,0,IF(D12=3,E12,IF(D12=4,E12,IF(D12=5,E12))))) -> 1182.4 | C51: Payout
A52: Placings | B52: 61-90
A53: 1 | B53: =IFERROR(HLOOKUP(B52,'Payout Schedule'!$B$1:$M$13,A53+1,0),"") -> 0.35 | C53: =IFERROR(B51*B53,"") -> 413.84
A54: 2 | B54: =IFERROR(HLOOKUP(B52,'Payout Schedule'!$B$1:$M$13,A54+1,0),"") -> 0.25 | C54: =IFERROR(B51*B54,"") -> 295.6
A55: 3 | B55: =IFERROR(HLOOKUP(B52,'Payout Schedule'!$B$1:$M$13,A55+1,0),"") -> 0.19 | C55: =IFERROR(B51*B55,"") -> 224.656
A56: 4 | B56: =IFERROR(HLOOKUP(B52,'Payout Schedule'!$B$1:$M$13,A56+1,0),"") -> 0.14 | C56: =IFERROR(B51*B56,"") -> 165.536
A57: 5 | B57: =IFERROR(HLOOKUP(B52,'Payout Schedule'!$B$1:$M$13,A57+1,0),"") -> 0.07 | C57: =IFERROR(B51*B57,"") -> 82.768
A58: 6 | B58: =IFERROR(HLOOKUP(B52,'Payout Schedule'!$B$1:$M$13,A58+1,0),"") | C58: =IFERROR(B51*B58,"") -> 0
A59: 7 | B59: =IFERROR(HLOOKUP(B52,'Payout Schedule'!$B$1:$M$13,A59+1,0),"") | C59: =IFERROR(B51*B59,"") -> 0
A60: 8 | B60: =IFERROR(HLOOKUP(B52,'Payout Schedule'!$B$1:$M$13,A60+1,0),"") | C60: =IFERROR(B51*B60,"") -> 0
A61: 9 | B61: =IFERROR(HLOOKUP(B52,'Payout Schedule'!$B$1:$M$13,A61+1,0),"") | C61: =IFERROR(B51*B61,"") -> 0
A62: 10 | B62: =IFERROR(HLOOKUP(B52,'Payout Schedule'!$B$1:$M$13,A62+1,0),"") | C62: =IFERROR(B51*B62,"") -> 0
A63: 11 | B63: =IFERROR(HLOOKUP(B52,'Payout Schedule'!$B$1:$M$13,A63+1,0),"") | C63: =IFERROR(B51*B63,"") -> 0
A64: 12 | B64: =IFERROR(HLOOKUP(B52,'Payout Schedule'!$B$1:$M$13,A64+1,0),"") | C64: =IFERROR(B51*B64,"") -> 0
A66: Total | B66: =SUM(B53:B64) -> 1 | C66: =SUM(C53:C64) -> 1182.4
B68: DELTA TEAM
B69: =IF(D12=1,0,IF(D12=2,0,IF(D12=3,0,IF(D12=4,E12,IF(D12=5,E12))))) -> 1182.4 | C69: Payout
A70: Placings | B70: 61-90
A71: 1 | B71: =IFERROR(HLOOKUP(B70,'Payout Schedule'!$B$1:$M$13,A71+1,0),"") -> 0.35 | C71: =IFERROR(B69*B71,"") -> 413.84
A72: 2 | B72: =IFERROR(HLOOKUP(B70,'Payout Schedule'!$B$1:$M$13,A72+1,0),"") -> 0.25 | C72: =IFERROR(B69*B72,"") -> 295.6
A73: 3 | B73: =IFERROR(HLOOKUP(B70,'Payout Schedule'!$B$1:$M$13,A73+1,0),"") -> 0.19 | C73: =IFERROR(B69*B73,"") -> 224.656
A74: 4 | B74: =IFERROR(HLOOKUP(B70,'Payout Schedule'!$B$1:$M$13,A74+1,0),"") -> 0.14 | C74: =IFERROR(B69*B74,"") -> 165.536
A75: 5 | B75: =IFERROR(HLOOKUP(B70,'Payout Schedule'!$B$1:$M$13,A75+1,0),"") -> 0.07 | C75: =IFERROR(B69*B75,"") -> 82.768
A76: 6 | B76: =IFERROR(HLOOKUP(B70,'Payout Schedule'!$B$1:$M$13,A76+1,0),"") | C76: =IFERROR(B69*B76,"") -> 0
A77: 7 | B77: =IFERROR(HLOOKUP(B70,'Payout Schedule'!$B$1:$M$13,A77+1,0),"") | C77: =IFERROR(B69*B77,"") -> 0
A78: 8 | B78: =IFERROR(HLOOKUP(B70,'Payout Schedule'!$B$1:$M$13,A78+1,0),"") | C78: =IFERROR(B69*B78,"") -> 0
A79: 9 | B79: =IFERROR(HLOOKUP(B70,'Payout Schedule'!$B$1:$M$13,A79+1,0),"") | C79: =IFERROR(B69*B79,"") -> 0
A80: 10 | B80: =IFERROR(HLOOKUP(B70,'Payout Schedule'!$B$1:$M$13,A80+1,0),"") | C80: =IFERROR(B69*B80,"") -> 0
A81: 11 | B81: =IFERROR(HLOOKUP(B70,'Payout Schedule'!$B$1:$M$13,A81+1,0),"") | C81: =IFERROR(B69*B81,"") -> 0
A82: 12 | B82: =IFERROR(HLOOKUP(B70,'Payout Schedule'!$B$1:$M$13,A82+1,0),"") | C82: =IFERROR(B69*B82,"") -> 0
A84: Total | B84: =SUM(B71:B82) -> 1 | C84: =SUM(C71:C82) -> 1182.4
B86: ECHO TEAM
B87: =IF(D12=1,0,IF(D12=2,0,IF(D12=3,0,IF(D12=4,0,IF(D12=5,E12))))) -> 1182.4 | C87: Payout
A88: Placings | B88: 61-90
A89: 1 | B89: =IFERROR(HLOOKUP(B88,'Payout Schedule'!$B$1:$M$13,A89+1,0),"") -> 0.35 | C89: =IFERROR(B87*B89,"") -> 413.84
A90: 2 | B90: =IFERROR(HLOOKUP(B88,'Payout Schedule'!$B$1:$M$13,A90+1,0),"") -> 0.25 | C90: =IFERROR(B87*B90,"") -> 295.6
A91: 3 | B91: =IFERROR(HLOOKUP(B88,'Payout Schedule'!$B$1:$M$13,A91+1,0),"") -> 0.19 | C91: =IFERROR(B87*B91,"") -> 224.656
A92: 4 | B92: =IFERROR(HLOOKUP(B88,'Payout Schedule'!$B$1:$M$13,A92+1,0),"") -> 0.14 | C92: =IFERROR(B87*B92,"") -> 165.536
A93: 5 | B93: =IFERROR(HLOOKUP(B88,'Payout Schedule'!$B$1:$M$13,A93+1,0),"") -> 0.07 | C93: =IFERROR(B87*B93,"") -> 82.768
A94: 6 | B94: =IFERROR(HLOOKUP(B88,'Payout Schedule'!$B$1:$M$13,A94+1,0),"") | C94: =IFERROR(B87*B94,"") -> 0
A95: 7 | B95: =IFERROR(HLOOKUP(B88,'Payout Schedule'!$B$1:$M$13,A95+1,0),"") | C95: =IFERROR(B87*B95,"") -> 0
A96: 8 | B96: =IFERROR(HLOOKUP(B88,'Payout Schedule'!$B$1:$M$13,A96+1,0),"") | C96: =IFERROR(B87*B96,"") -> 0
A97: 9 | B97: =IFERROR(HLOOKUP(B88,'Payout Schedule'!$B$1:$M$13,A97+1,0),"") | C97: =IFERROR(B87*B97,"") -> 0
A98: 10 | B98: =IFERROR(HLOOKUP(B88,'Payout Schedule'!$B$1:$M$13,A98+1,0),"") | C98: =IFERROR(B87*B98,"") -> 0
A99: 11 | B99: =IFERROR(HLOOKUP(B88,'Payout Schedule'!$B$1:$M$13,A99+1,0),"") | C99: =IFERROR(B87*B99,"") -> 0
A100: 12 | B100: =IFERROR(HLOOKUP(B88,'Payout Schedule'!$B$1:$M$13,A100+1,0),"") | C100: =IFERROR(B87*B100,"") -> 0
A102: Total | B102: =SUM(B89:B100) -> 1 | C102: =SUM(C89:C100) -> 1182.4

Sheet Danny Dietz Race
A3: Membership | B3: # of Contestents | C3: Entry Fee | D3: Gross Pot | E3: Processing Fees 4% | F3: Gross to Pay
A4: 0 | B4: 150 | C4: 90 | D4: =B4*C4 -> 13500 | E4: =D4*4% -> 540 | F4: =D4-E4 -> 12960 | G4: Payback/Holdings
F5: PR HOLDING | G5: 0.5 | H5: =F4*G5 -> 6480
F6: RACERS POT | G6: 0.5 | H6: =F4*G6 -> 6480
G7: =SUM(G5:G6) -> 1 | H7: =SUM(H5:H6) -> 12960
B8: =F10 | C8: True Added $ | D8: Contestant payback + True Added $
B9: =H6 -> 6480 | C9: 0 | D9: =B9+C9 -> 6480 | G9: PR | H9: 0.5 | I9: =H9*H5 -> 3240
G10: Producer | H10: 0.5 | I10: =H10*H5 -> 3240
B11: D1 Added $ | C11: Contestent Payback - D1 Added $ | D11: # of Contestent Divisions | E11: Even Division Payouts | H11: =SUM(H9:H10) -> 1
B12: 1000 | C12: =D9-B12 -> 5480 | D12: 5 | E12: =C12/D12 -> 1096
G13: Sponsorship | H13: Difference | I13: PR NET
B14: ALPHA TEAM | G14: 0 | H14: =I10-G14 -> 3240 | I14: =IF(OR(I9<0, H14<0), SUM(I9,H14), I9) -> 3240
B15: =B12+E12 -> 2096 | C15: Payout | D15: TOTAL DIVISIONS PAYOUT (Color box should Match)
A16: Placings | B16: 121-150 | D16: =sum(C30,C48,C66,C84,C102) -> 6480 | I16: Producer NET
A17: 1 | B17: =IFERROR(HLOOKUP(B16,'Payout Schedule'!$B$1:$M$13,A17+1,0),"") -> 0.3 | C17: =IFERROR(B15*B17,"") -> 628.8 | I17: =IF(I10 > G14, I10, G14) -> 3240
A18: 2 | B18: =IFERROR(HLOOKUP(B16,'Payout Schedule'!$B$1:$M$13,A18+1,0),"") -> 0.21 | C18: =IFERROR(B15*B18,"") -> 440.16
A19: 3 | B19: =IFERROR(HLOOKUP(B16,'Payout Schedule'!$B$1:$M$13,A19+1,0),"") -> 0.16 | C19: =IFERROR(B15*B19,"") -> 335.36 | I19: PR Membership
A20: 4 | B20: =IFERROR(HLOOKUP(B16,'Payout Schedule'!$B$1:$M$13,A20+1,0),"") -> 0.12 | C20: =IFERROR(B15*B20,"") -> 251.52 | G20: Membership Sales | H20: Rebate | I20: =G21-I22 -> 0
A21: 5 | B21: =IFERROR(HLOOKUP(B16,'Payout Schedule'!$B$1:$M$13,A21+1,0),"") -> 0.09 | C21: =IFERROR(B15*B21,"") -> 188.64 | G21: =A4*B4 -> 0 | H21: 0 | I21: Producer Rebate
A22: 6 | B22: =IFERROR(HLOOKUP(B16,'Payout Schedule'!$B$1:$M$13,A22+1,0),"") -> 0.07 | C22: =IFERROR(B15*B22,"") -> 146.72 | I22: =B4*H21 -> 0
A23: 7 | B23: =IFERROR(HLOOKUP(B16,'Payout Schedule'!$B$1:$M$13,A23+1,0),"") -> 0.05 | C23: =IFERROR(B15*B23,"") -> 104.8
A24: 8 | B24: =IFERROR(HLOOKUP(B16,'Payout Schedule'!$B$1:$M$13,A24+1,0),"") | C24: =IFERROR(B15*B24,"") -> 0 | E24: RACE SNAPSHOT
A25: 9 | B25: =IFERROR(HLOOKUP(B16,'Payout Schedule'!$B$1:$M$13,A25+1,0),"") | C25: =IFERROR(B15*B25,"") -> 0 | E25: CONTESTANTS | F25: =D9 -> 6480
A26: 10 | B26: =IFERROR(HLOOKUP(B16,'Payout Schedule'!$B$1:$M$13,A26+1,0),"") | C26: =IFERROR(B15*B26,"") -> 0 | E26: PROMOTER | F26: =I22+I17 -> 3240
A27: 11 | B27: =IFERROR(HLOOKUP(B16,'Payout Schedule'!$B$1:$M$13,A27+1,0),"") | C27: =IFERROR(B15*B27,"") -> 0 | E27: PEER RACING | F27: =I9+I20 -> 3240
A28: 12 | B28: =IFERROR(HLOOKUP(B16,'Payout Schedule'!$B$1:$M$13,A28+1,0),"") | C28: =IFERROR(B15*B28,"") -> 0
A30: Total | B30: =SUM(B17:B28) -> 1 | C30: =SUM(C17:C28) -> 2096
B32: BRAVO TEAM
B33: =IF(D12=1,0,IF(D12=2,E12,IF(D12=3,E12,IF(D12=4,E12,IF(D12=5,E12))))) -> 1096 | C33: Payout
A34: Placings | B34: 121-150
A35: 1 | B35: =IFERROR(HLOOKUP(B34,'Payout Schedule'!$B$1:$M$13,A35+1,0),"") -> 0.3 | C35: =IFERROR(B33*B35,"") -> 328.8
A36: 2 | B36: =IFERROR(HLOOKUP(B34,'Payout Schedule'!$B$1:$M$13,A36+1,0),"") -> 0.21 | C36: =IFERROR(B33*B36,"") -> 230.16
A37: 3 | B37: =IFERROR(HLOOKUP(B34,'Payout Schedule'!$B$1:$M$13,A37+1,0),"") -> 0.16 | C37: =IFERROR(B33*B37,"") -> 175.36
A38: 4 | B38: =IFERROR(HLOOKUP(B34,'Payout Schedule'!$B$1:$M$13,A38+1,0),"") -> 0.12 | C38: =IFERROR(B33*B38,"") -> 131.52
A39: 5 | B39: =IFERROR(HLOOKUP(B34,'Payout Schedule'!$B$1:$M$13,A39+1,0),"") -> 0.09 | C39: =IFERROR(B33*B39,"") -> 98.64
A40: 6 | B40: =IFERROR(HLOOKUP(B34,'Payout Schedule'!$B$1:$M$13,A40+1,0),"") -> 0.07 | C40: =IFERROR(B33*B40,"") -> 76.72
A41: 7 | B41: =IFERROR(HLOOKUP(B34,'Payout Schedule'!$B$1:$M$13,A41+1,0),"") -> 0.05 | C41: =IFERROR(B33*B41,"") -> 54.8
A42: 8 | B42: =IFERROR(HLOOKUP(B34,'Payout Schedule'!$B$1:$M$13,A42+1,0),"") | C42: =IFERROR(B33*B42,"") -> 0
A43: 9 | B43: =IFERROR(HLOOKUP(B34,'Payout Schedule'!$B$1:$M$13,A43+1,0),"") | C43: =IFERROR(B33*B43,"") -> 0
A44: 10 | B44: =IFERROR(HLOOKUP(B34,'Payout Schedule'!$B$1:$M$13,A44+1,0),"") | C44: =IFERROR(B33*B44,"") -> 0
A45: 11 | B45: =IFERROR(HLOOKUP(B34,'Payout Schedule'!$B$1:$M$13,A45+1,0),"") | C45: =IFERROR(B33*B45,"") -> 0
A46: 12 | B46: =IFERROR(HLOOKUP(B34,'Payout Schedule'!$B$1:$M$13,A46+1,0),"") | C46: =IFERROR(B33*B46,"") -> 0
A48: Total | B48: =SUM(B35:B46) -> 1 | C48: =SUM(C35:C46) -> 1096
B50: CHARLIE TEAM
B51: =IF(D12=1,0,IF(D12=2,0,IF(D12=3,E12,IF(D12=4,E12,IF(D12=5,E12))))) -> 1096 | C51: Payout
A52: Placings | B52: 121-150
A53: 1 | B53: =IFERROR(HLOOKUP(B52,'Payout Schedule'!$B$1:$M$13,A53+1,0),"") -> 0.3 | C53: =IFERROR(B51*B53,"") -> 328.8
A54: 2 | B54: =IFERROR(HLOOKUP(B52,'Payout Schedule'!$B$1:$M$13,A54+1,0),"") -> 0.21 | C54: =IFERROR(B51*B54,"") -> 230.16
A55: 3 | B55: =IFERROR(HLOOKUP(B52,'Payout Schedule'!$B$1:$M$13,A55+1,0),"") -> 0.16 | C55: =IFERROR(B51*B55,"") -> 175.36
A56: 4 | B56: =IFERROR(HLOOKUP(B52,'Payout Schedule'!$B$1:$M$13,A56+1,0),"") -> 0.12 | C56: =IFERROR(B51*B56,"") -> 131.52
A57: 5 | B57: =IFERROR(HLOOKUP(B52,'Payout Schedule'!$B$1:$M$13,A57+1,0),"") -> 0.09 | C57: =IFERROR(B51*B57,"") -> 98.64
A58: 6 | B58: =IFERROR(HLOOKUP(B52,'Payout Schedule'!$B$1:$M$13,A58+1,0),"") -> 0.07 | C58: =IFERROR(B51*B58,"") -> 76.72
A59: 7 | B59: =IFERROR(HLOOKUP(B52,'Payout Schedule'!$B$1:$M$13,A59+1,0),"") -> 0.05 | C59: =IFERROR(B51*B59,"") -> 54.8
A60: 8 | B60: =IFERROR(HLOOKUP(B52,'Payout Schedule'!$B$1:$M$13,A60+1,0),"") | C60: =IFERROR(B51*B60,"") -> 0
A61: 9 | B61: =IFERROR(HLOOKUP(B52,'Payout Schedule'!$B$1:$M$13,A61+1,0),"") | C61: =IFERROR(B51*B61,"") -> 0
A62: 10 | B62: =IFERROR(HLOOKUP(B52,'Payout Schedule'!$B$1:$M$13,A62+1,0),"") | C62: =IFERROR(B51*B62,"") -> 0
A63: 11 | B63: =IFERROR(HLOOKUP(B52,'Payout Schedule'!$B$1:$M$13,A63+1,0),"") | C63: =IFERROR(B51*B63,"") -> 0
A64: 12 | B64: =IFERROR(HLOOKUP(B52,'Payout Schedule'!$B$1:$M$13,A64+1,0),"") | C64: =IFERROR(B51*B64,"") -> 0
A66: Total | B66: =SUM(B53:B64) -> 1 | C66: =SUM(C53:C64) -> 1096
B68: DELTA TEAM
B69: =IF(D12=1,0,IF(D12=2,0,IF(D12=3,0,IF(D12=4,E12,IF(D12=5,E12))))) -> 1096 | C69: Payout
A70: Placings | B70: 121-150
A71: 1 | B71: =IFERROR(HLOOKUP(B70,'Payout Schedule'!$B$1:$M$13,A71+1,0),"") -> 0.3 | C71: =IFERROR(B69*B71,"") -> 328.8
A72: 2 | B72: =IFERROR(HLOOKUP(B70,'Payout Schedule'!$B$1:$M$13,A72+1,0),"") -> 0.21 | C72: =IFERROR(B69*B72,"") -> 230.16
A73: 3 | B73: =IFERROR(HLOOKUP(B70,'Payout Schedule'!$B$1:$M$13,A73+1,0),"") -> 0.16 | C73: =IFERROR(B69*B73,"") -> 175.36
A74: 4 | B74: =IFERROR(HLOOKUP(B70,'Payout Schedule'!$B$1:$M$13,A74+1,0),"") -> 0.12 | C74: =IFERROR(B69*B74,"") -> 131.52
A75: 5 | B75: =IFERROR(HLOOKUP(B70,'Payout Schedule'!$B$1:$M$13,A75+1,0),"") -> 0.09 | C75: =IFERROR(B69*B75,"") -> 98.64
A76: 6 | B76: =IFERROR(HLOOKUP(B70,'Payout Schedule'!$B$1:$M$13,A76+1,0),"") -> 0.07 | C76: =IFERROR(B69*B76,"") -> 76.72
A77: 7 | B77: =IFERROR(HLOOKUP(B70,'Payout Schedule'!$B$1:$M$13,A77+1,0),"") -> 0.05 | C77: =IFERROR(B69*B77,"") -> 54.8
A78: 8 | B78: =IFERROR(HLOOKUP(B70,'Payout Schedule'!$B$1:$M$13,A78+1,0),"") | C78: =IFERROR(B69*B78,"") -> 0
A79: 9 | B79: =IFERROR(HLOOKUP(B70,'Payout Schedule'!$B$1:$M$13,A79+1,0),"") | C79: =IFERROR(B69*B79,"") -> 0
A80: 10 | B80: =IFERROR(HLOOKUP(B70,'Payout Schedule'!$B$1:$M$13,A80+1,0),"") | C80: =IFERROR(B69*B80,"") -> 0
A81: 11 | B81: =IFERROR(HLOOKUP(B70,'Payout Schedule'!$B$1:$M$13,A81+1,0),"") | C81: =IFERROR(B69*B81,"") -> 0
A82: 12 | B82: =IFERROR(HLOOKUP(B70,'Payout Schedule'!$B$1:$M$13,A82+1,0),"") | C82: =IFERROR(B69*B82,"") -> 0
A84: Total | B84: =SUM(B71:B82) -> 1 | C84: =SUM(C71:C82) -> 1096
B86: ECHO TEAM
B87: =IF(D12=1,0,IF(D12=2,0,IF(D12=3,0,IF(D12=4,0,IF(D12=5,E12))))) -> 1096 | C87: Payout
A88: Placings | B88: 121-150
A89: 1 | B89: =IFERROR(HLOOKUP(B88,'Payout Schedule'!$B$1:$M$13,A89+1,0),"") -> 0.3 | C89: =IFERROR(B87*B89,"") -> 328.8
A90: 2 | B90: =IFERROR(HLOOKUP(B88,'Payout Schedule'!$B$1:$M$13,A90+1,0),"") -> 0.21 | C90: =IFERROR(B87*B90,"") -> 230.16
A91: 3 | B91: =IFERROR(HLOOKUP(B88,'Payout Schedule'!$B$1:$M$13,A91+1,0),"") -> 0.16 | C91: =IFERROR(B87*B91,"") -> 175.36
A92: 4 | B92: =IFERROR(HLOOKUP(B88,'Payout Schedule'!$B$1:$M$13,A92+1,0),"") -> 0.12 | C92: =IFERROR(B87*B92,"") -> 131.52
A93: 5 | B93: =IFERROR(HLOOKUP(B88,'Payout Schedule'!$B$1:$M$13,A93+1,0),"") -> 0.09 | C93: =IFERROR(B87*B93,"") -> 98.64
A94: 6 | B94: =IFERROR(HLOOKUP(B88,'Payout Schedule'!$B$1:$M$13,A94+1,0),"") -> 0.07 | C94: =IFERROR(B87*B94,"") -> 76.72
A95: 7 | B95: =IFERROR(HLOOKUP(B88,'Payout Schedule'!$B$1:$M$13,A95+1,0),"") -> 0.05 | C95: =IFERROR(B87*B95,"") -> 54.8
A96: 8 | B96: =IFERROR(HLOOKUP(B88,'Payout Schedule'!$B$1:$M$13,A96+1,0),"") | C96: =IFERROR(B87*B96,"") -> 0
A97: 9 | B97: =IFERROR(HLOOKUP(B88,'Payout Schedule'!$B$1:$M$13,A97+1,0),"") | C97: =IFERROR(B87*B97,"") -> 0
A98: 10 | B98: =IFERROR(HLOOKUP(B88,'Payout Schedule'!$B$1:$M$13,A98+1,0),"") | C98: =IFERROR(B87*B98,"") -> 0
A99: 11 | B99: =IFERROR(HLOOKUP(B88,'Payout Schedule'!$B$1:$M$13,A99+1,0),"") | C99: =IFERROR(B87*B99,"") -> 0
A100: 12 | B100: =IFERROR(HLOOKUP(B88,'Payout Schedule'!$B$1:$M$13,A100+1,0),"") | C100: =IFERROR(B87*B100,"") -> 0
A102: Total | B102: =SUM(B89:B100) -> 1 | C102: =SUM(C89:C100) -> 1096

Sheet MAIN P&L (make copies)
B2: Event Budget Spreadsheet
B6: Total | C6: =SUMIF($B:$B, "Subtotal", C:C) -> 0 | D6: =SUMIF($B:$B, "Subtotal", D:D) -> 0 | E6: =SUMIF($B:$B, "Subtotal", E:E) -> 0
B7: Expenses | C7: Budgeted | D7: Actual | E7: Variation
B9: INCOME
B10: 5K ENTRIES | C10: 0 | D10: 0 | E10: =ABS(MINUS(C10,D10)) -> 0
B11: 10K ENTRIES | C11: 0 | D11: 0 | E11: =ABS(MINUS(C11,D11)) -> 0
B12: 1/2M ENTRIES | C12: 0 | D12: 0 | E12: =ABS(MINUS(C12,D12)) -> 0
B13: MEMBERSHIPS | C13: 0 | D13: 0 | E13: =ABS(MINUS(C13,D13)) -> 0
B14: Apparrel Sales | C14: 0 | D14: 0 | E14: =ABS(MINUS(C14,D14)) -> 0
B16: Subtotal | C16: =SUM(C10:C14) -> 0 | D16: =SUM(D10:D14) -> 0 | E16: =SUM(E10:E14) -> 0
B18: Facility
B19: Venue rental | C19: 0 | D19: 0 | E19: =ABS(MINUS(C19,D19)) -> 0
B20: Security deposit | C20: 0 | D20: 0 | E20: =ABS(MINUS(C20,D20)) -> 0
B21: Insurance | C21: 0 | D21: 0 | E21: =ABS(MINUS(C21,D21)) -> 0
B22: Utilities (electricity, water) | C22: 0 | D22: 0 | E22: =ABS(MINUS(C22,D22)) -> 0
B23: Cleaning services | C23: 0 | D23: 0 | E23: =ABS(MINUS(C23,D23)) -> 0
B25: Subtotal | C25: =SUM(C19:C23) -> 0 | D25: =SUM(D19:D23) -> 0 | E25: =SUM(E19:E23) -> 0
B27: Promotions
B28: Advertising | C28: 0 | D28: 0 | E28: =ABS(MINUS(C28,D28)) -> 0
B29: Printing and design | C29: 0 | D29: 0 | E29: =ABS(MINUS(C29,D29)) -> 0
B30: Digital marketing | C30: 0 | D30: 0 | E30: =ABS(MINUS(C30,D30)) -> 0
B31: Social media promotion | C31: 0 | D31: 0 | E31: =ABS(MINUS(C31,D31)) -> 0
B32: Public relations | C32: 0 | D32: 0 | E32: =ABS(MINUS(C32,D32)) -> 0
B34: Subtotal | C34: =SUM(C28:C32) -> 0 | D34: =SUM(D28:D32) -> 0 | E34: =SUM(E28:E32) -> 0
B36: Registration Expenses
B37: Online registration system | C37: 0 | D37: 0 | E37: =ABS(MINUS(C37,D37)) -> 0
B38: Registration materials (badges, lanyards, etc.) | C38: 0 | D38: 0 | E38: =ABS(MINUS(C38,D38)) -> 0
B39: On-site registration staff | C39: 0 | D39: 0 | E39: =ABS(MINUS(C39,D39)) -> 0
B40: Attendee welcome packs | C40: 0 | D40: 0 | E40: =ABS(MINUS(C40,D40)) -> 0
B41: Name tags | C41: 0 | D41: 0 | E41: =ABS(MINUS(C41,D41)) -> 0
B43: Subtotal | C43: =SUM(C37:C41) -> 0 | D43: =SUM(D37:D41) -> 0 | E43: =SUM(E37:E41) -> 0
B45: Speakers and Presenters Expenses
B46: Speaker fees | C46: 0 | D46: 0 | E46: =ABS(MINUS(C46,D46)) -> 0
B47: Travel expenses (flights, accommodation) | C47: 0 | D47: 0 | E47: =ABS(MINUS(C47,D47)) -> 0
B48: Speaker gifts or honorariums | C48: 0 | D48: 0 | E48: =ABS(MINUS(C48,D48)) -> 0
B49: AV equipment for presentations | C49: 0 | D49: 0 | E49: =ABS(MINUS(C49,D49)) -> 0
B50: Technical support staff | C50: 0 | D50: 0 | E50: =ABS(MINUS(C50,D50)) -> 0
B52: Subtotal | C52: =SUM(C46:C50) -> 0 | D52: =SUM(D46:D50) -> 0 | E52: =SUM(E46:E50) -> 0
B54: Food and Beverage Expenses
B55: Catering (meals, snacks, beverages) | C55: 0 | D55: 0 | E55: =ABS(MINUS(C55,D55)) -> 0
B56: Coffee breaks | C56: 0 | D56: 0 | E56: =ABS(MINUS(C56,D56)) -> 0
B57: Welcome reception | C57: 0 | D57: 0 | E57: =ABS(MINUS(C57,D57)) -> 0
B58: Dietary restrictions accommodation | C58: 0 | D58: 0 | E58: =ABS(MINUS(C58,D58)) -> 0
B59: Bar services | C59: 0 | D59: 0 | E59: =ABS(MINUS(C59,D59)) -> 0
B61: Subtotal | C61: =SUM(C55:C59) -> 0 | D61: =SUM(D55:D59) -> 0 | E61: =SUM(E55:E59) -> 0
B63: Audiovisual Expenses
B64: Sound system and equipment rental | C64: 0 | D64: 0 | E64: =ABS(MINUS(C64,D64)) -> 0
B65: Projection equipment | C65: 0 | D65: 0 | E65: =ABS(MINUS(C65,D65)) -> 0
B66: Lighting and stage setup | C66: 0 | D66: 0 | E66: =ABS(MINUS(C66,D66)) -> 0
B67: Videography and live streaming services | C67: 0 | D67: 0 | E67: =ABS(MINUS(C67,D67)) -> 0
B68: Technical crew and support staff | C68: 0 | D68: 0 | E68: =ABS(MINUS(C68,D68)) -> 0
B70: Subtotal | C70: =SUM(C64:C68) -> 0 | D70: =SUM(D64:D68) -> 0 | E70: =SUM(E64:E68) -> 0
B72: Decorations
B73: Theme decor | C73: 0 | D73: 0 | E73: =ABS(MINUS(C73,D73)) -> 0
B74: Table centerpieces | C74: 0 | D74: 0 | E74: =ABS(MINUS(C74,D74)) -> 0
B75: Floral arrangements | C75: 0 | D75: 0 | E75: =ABS(MINUS(C75,D75)) -> 0
B76: Balloons | C76: 0 | D76: 0 | E76: =ABS(MINUS(C76,D76)) -> 0
B77: Signage and banners | C77: 0 | D77: 0 | E77: =ABS(MINUS(C77,D77)) -> 0
B79: Subtotal | C79: =SUM(C73:C77) -> 0 | D79: =SUM(D73:D77) -> 0 | E79: =SUM(E73:E77) -> 0
B81: Transportation Expenses
B82: Transportation for organizers and staff | C82: 0 | D82: 0 | E82: =ABS(MINUS(C82,D82)) -> 0
B83: Shuttle service for attendees | C83: 0 | D83: 0 | E83: =ABS(MINUS(C83,D83)) -> 0
B84: Parking fees | C84: 0 | D84: 0 | E84: =ABS(MINUS(C84,D84)) -> 0
B85: Rental vehicles | C85: 0 | D85: 0 | E85: =ABS(MINUS(C85,D85)) -> 0
B86: Driver services | C86: 0 | D86: 0 | E86: =ABS(MINUS(C86,D86)) -> 0
B88: Subtotal | C88: =SUM(C82:C86) -> 0 | D88: =SUM(D82:D86) -> 0 | E88: =SUM(E82:E86) -> 0
B90: Miscellaneous
B91: Event management software | C91: 0 | D91: 0 | E91: =ABS(MINUS(C91,D91)) -> 0
B92: Wi-Fi and internet access | C92: 0 | D92: 0 | E92: =ABS(MINUS(C92,D92)) -> 0
B93: Printing and stationery | C93: 0 | D93: 0 | E93: =ABS(MINUS(C93,D93)) -> 0
B94: Photography and videography services | C94: 0 | D94: 0 | E94: =ABS(MINUS(C94,D94)) -> 0
B95: Staff and volunteers | C95: 0 | D95: 0 | E95: =ABS(MINUS(C95,D95)) -> 0
B97: Subtotal | C97: =SUM(C91:C95) -> 0 | D97: =SUM(D91:D95) -> 0 | E97: =SUM(E91:E95) -> 0

Sheet Race Results
A2: TOTAL RUNNERS PAYOUT
B3: ='Master Calculator'!D9 -> 7200
A5: Alpha Team | B5: ='Master Calculator'!B15 -> 1440 | C5: Overall Finish | D5: First | E5: Last | F5: Time
A6: 1st | B6: ='Master Calculator'!C17 -> 475.2
A7: 2nd | B7: ='Master Calculator'!C18 -> 331.2
A8: 3rd | B8: ='Master Calculator'!C19 -> 244.8
A9: 4th | B9: ='Master Calculator'!C20 -> 172.8
A10: 5th | B10: ='Master Calculator'!C21 -> 129.6
A11: 6th | B11: ='Master Calculator'!C22 -> 86.4
A12: 7th | B12: ='Master Calculator'!C23 -> 0
A13: 8th | B13: ='Master Calculator'!C24 -> 0
A14: 9th | B14: ='Master Calculator'!C25 -> 0
A15: 10th | B15: ='Master Calculator'!C26 -> 0
A16: 11th | B16: ='Master Calculator'!C27 -> 0
A17: 12th | B17: ='Master Calculator'!C28 -> 0
B18: ='Master Calculator'!C29
A19: Bravo Team | B19: ='Master Calculator'!B33 -> 1440 | C19: Overall Finish | D19: First | E19: Last | F19: Time
A20: 1st | B20: ='Master Calculator'!C35 -> 475.2
A21: 2nd | B21: ='Master Calculator'!C36 -> 331.2
A22: 3rd | B22: ='Master Calculator'!C37 -> 244.8
A23: 4th | B23: ='Master Calculator'!C38 -> 172.8
A24: 5th | B24: ='Master Calculator'!C39 -> 129.6
A25: 6th | B25: ='Master Calculator'!C40 -> 86.4
A26: 7th | B26: ='Master Calculator'!C41 -> 0
A27: 8th | B27: ='Master Calculator'!C42 -> 0
A28: 9th | B28: ='Master Calculator'!C43 -> 0
A29: 10th | B29: ='Master Calculator'!C44 -> 0
A30: 11th | B30: ='Master Calculator'!C45 -> 0
A31: 12th | B31: ='Master Calculator'!C46 -> 0
A33: Charlie Team | B33: ='Master Calculator'!B51 -> 1440 | C33: Overall Finish | D33: First | E33: Last | F33: Time
A34: 1st | B34: ='Master Calculator'!C53 -> 475.2
A35: 2nd | B35: ='Master Calculator'!C54 -> 331.2
A36: 3rd | B36: ='Master Calculator'!C55 -> 244.8
A37: 4th | B37: ='Master Calculator'!C56 -> 172.8
A38: 5th | B38: ='Master Calculator'!C57 -> 129.6
A39: 6th | B39: ='Master Calculator'!C58 -> 86.4
A40: 7th | B40: ='Master Calculator'!C59 -> 0
A41: 8th | B41: ='Master Calculator'!C60 -> 0
A42: 9th | B42: ='Master Calculator'!C61 -> 0
A43: 10th | B43: ='Master Calculator'!C62 -> 0
A44: 11th | B44: ='Master Calculator'!C63 -> 0
A45: 12th | B45: ='Master Calculator'!C64 -> 0
A47: Delta Team | B47: ='Master Calculator'!B69 -> 1440 | C47: Overall Finish | D47: First | E47: Last | F47: Time
A48: 1st | B48: ='Master Calculator'!C71 -> 475.2
A49: 2nd | B49: ='Master Calculator'!C72 -> 331.2
A50: 3rd | B50: ='Master Calculator'!C73 -> 244.8
A51: 4th | B51: ='Master Calculator'!C74 -> 172.8
A52: 5th | B52: ='Master Calculator'!C75 -> 129.6
A53: 6th | B53: ='Master Calculator'!C76 -> 86.4
A54: 7th | B54: ='Master Calculator'!C77 -> 0
A55: 8th | B55: ='Master Calculator'!C78 -> 0
A56: 9th | B56: ='Master Calculator'!C79 -> 0
A57: 10th | B57: ='Master Calculator'!C80 -> 0
A58: 11th | B58: ='Master Calculator'!C81 -> 0
A59: 12th | B59: ='Master Calculator'!C82 -> 0
A61: Echo Team | B61: ='Master Calculator'!B87 -> 1440 | C61: Overall Finish | D61: First | E61: Last | F61: Time
A62: 1st | B62: ='Master Calculator'!C89 -> 475.2
A63: 2nd | B63: ='Master Calculator'!C90 -> 331.2
A64: 3rd | B64: ='Master Calculator'!C91 -> 244.8
A65: 4th | B65: ='Master Calculator'!C92 -> 172.8
A66: 5th | B66: ='Master Calculator'!C93 -> 129.6
A67: 6th | B67: ='Master Calculator'!C94 -> 86.4
A68: 7th | B68: ='Master Calculator'!C95 -> 0
A69: 8th | B69: ='Master Calculator'!C96 -> 0
A70: 9th | B70: ='Master Calculator'!C97 -> 0
A71: 10th | B71: ='Master Calculator'!C98 -> 0
A72: 11th | B72: ='Master Calculator'!C99 -> 0
A73: 12th | B73: ='Master Calculator'!C100 -> 0

Sheet Guaranteed Payout
A3: Membership | B3: # of Contestents | C3: Entry Fee | D3: Gross Pot | E3: Processing Fees 4% | F3: Gross to Pay
A4: 45 | B4: 900 | C4: 240 | D4: =B4*C4 -> 216000 | E4: =D4*4% -> 8640 | F4: =D4-E4 -> 207360 | G4: Payback/Holdings
F5: PR HOLDING | G5: 1 | H5: =F4*G5 -> 207360
F6: RACERS POT | G6: 0 | H6: =F4*G6 -> 0
G7: =SUM(G5:G6) -> 1 | H7: =SUM(H5:H6) -> 207360
B8: =F10 | C8: True Added $ | D8: Contestant payback + True Added $ | E8: Producer Holding less Added Money
B9: =H6 -> 0 | C9: 200000 | D9: =B9+C9 -> 200000 | E9: =H5-C9 -> 7360 | G9: PR | H9: 0.6 | I9: =H9*H5 -> 124416
G10: Producer | H10: 0.4 | I10: =H10*H5 -> 82944
A11: D1 Added $ | B11: D2 Added $ | C11: Contestent Payback - D1 Added $ | D11: # of Contestent Divisions | E11: Even Division Payouts | H11: =SUM(H9:H10) -> 1
A12: 20000 | B12: 20000 | C12: =D9-A12-B12 -> 160000 | D12: 10 | E12: =C12/D12 -> 16000
G13: Sponsorship | H13: Difference | I13: PR NET
B14: ALPHA OR MENS | G14: 0 | H14: =I10-G14 -> 82944 | I14: =IF(OR(I9<0, H14<0), SUM(I9,H14), I9) -> 124416
B15: =A12+E12 -> 36000 | C15: Payout | E15: TOTAL DIVISIONS PAYOUT (Color box should Match)
A16: Placings | B16: 271-300 | E16: =sum(C30,C48,C66,C84,C102,C121,C139,C157,C175,C193) -> 200000 | I16: Producer NET
A17: 1 | B17: =IFERROR(HLOOKUP(B16,'Payout Schedule'!$B$1:$M$13,A17+1,0),"") -> 0.22 | C17: =IFERROR(B15*B17,"") -> 7920 | I17: =IF(I10 > G14, I10, G14) -> 82944
A18: 2 | B18: =IFERROR(HLOOKUP(B16,'Payout Schedule'!$B$1:$M$13,A18+1,0),"") -> 0.17 | C18: =IFERROR(B15*B18,"") -> 6120
A19: 3 | B19: =IFERROR(HLOOKUP(B16,'Payout Schedule'!$B$1:$M$13,A19+1,0),"") -> 0.12 | C19: =IFERROR(B15*B19,"") -> 4320 | I19: PR Membership
A20: 4 | B20: =IFERROR(HLOOKUP(B16,'Payout Schedule'!$B$1:$M$13,A20+1,0),"") -> 0.09 | C20: =IFERROR(B15*B20,"") -> 3240 | G20: Membership Sales | H20: Rebate | I20: =G21-I22 -> 40500
A21: 5 | B21: =IFERROR(HLOOKUP(B16,'Payout Schedule'!$B$1:$M$13,A21+1,0),"") -> 0.08 | C21: =IFERROR(B15*B21,"") -> 2880 | G21: =A4*B4 -> 40500 | H21: 0 | I21: Producer Rebate
A22: 6 | B22: =IFERROR(HLOOKUP(B16,'Payout Schedule'!$B$1:$M$13,A22+1,0),"") -> 0.07 | C22: =IFERROR(B15*B22,"") -> 2520 | I22: =B4*H21 -> 0
A23: 7 | B23: =IFERROR(HLOOKUP(B16,'Payout Schedule'!$B$1:$M$13,A23+1,0),"") -> 0.06 | C23: =IFERROR(B15*B23,"") -> 2160
A24: 8 | B24: =IFERROR(HLOOKUP(B16,'Payout Schedule'!$B$1:$M$13,A24+1,0),"") -> 0.05 | C24: =IFERROR(B15*B24,"") -> 1800 | E24: RACE SNAPSHOT
A25: 9 | B25: =IFERROR(HLOOKUP(B16,'Payout Schedule'!$B$1:$M$13,A25+1,0),"") -> 0.04 | C25: =IFERROR(B15*B25,"") -> 1440 | E25: CONTESTANTS | F25: =D9 -> 200000
A26: 10 | B26: =IFERROR(HLOOKUP(B16,'Payout Schedule'!$B$1:$M$13,A26+1,0),"") -> 0.04 | C26: =IFERROR(B15*B26,"") -> 1440 | E26: PROMOTER | F26: =I22+I17 -> 82944
A27: 11 | B27: =IFERROR(HLOOKUP(B16,'Payout Schedule'!$B$1:$M$13,A27+1,0),"") -> 0.03 | C27: =IFERROR(B15*B27,"") -> 1080 | E27: PEER RACING | F27: =I9+I20 -> 164916
A28: 12 | B28: =IFERROR(HLOOKUP(B16,'Payout Schedule'!$B$1:$M$13,A28+1,0),"") -> 0.03 | C28: =IFERROR(B15*B28,"") -> 1080
A30: Total | B30: =SUM(B17:B28) -> 1 | C30: =SUM(C17:C28) -> 36000
B32: BRAVO OR FEMALE
B33: =B12+E12 -> 36000 | C33: Payout
A34: Placings | B34: 271-300
A35: 1 | B35: =IFERROR(HLOOKUP(B34,'Payout Schedule'!$B$1:$M$13,A35+1,0),"") -> 0.22 | C35: =IFERROR(B33*B35,"") -> 7920
A36: 2 | B36: =IFERROR(HLOOKUP(B34,'Payout Schedule'!$B$1:$M$13,A36+1,0),"") -> 0.17 | C36: =IFERROR(B33*B36,"") -> 6120
A37: 3 | B37: =IFERROR(HLOOKUP(B34,'Payout Schedule'!$B$1:$M$13,A37+1,0),"") -> 0.12 | C37: =IFERROR(B33*B37,"") -> 4320
A38: 4 | B38: =IFERROR(HLOOKUP(B34,'Payout Schedule'!$B$1:$M$13,A38+1,0),"") -> 0.09 | C38: =IFERROR(B33*B38,"") -> 3240
A39: 5 | B39: =IFERROR(HLOOKUP(B34,'Payout Schedule'!$B$1:$M$13,A39+1,0),"") -> 0.08 | C39: =IFERROR(B33*B39,"") -> 2880
A40: 6 | B40: =IFERROR(HLOOKUP(B34,'Payout Schedule'!$B$1:$M$13,A40+1,0),"") -> 0.07 | C40: =IFERROR(B33*B40,"") -> 2520
A41: 7 | B41: =IFERROR(HLOOKUP(B34,'Payout Schedule'!$B$1:$M$13,A41+1,0),"") -> 0.06 | C41: =IFERROR(B33*B41,"") -> 2160
A42: 8 | B42: =IFERROR(HLOOKUP(B34,'Payout Schedule'!$B$1:$M$13,A42+1,0),"") -> 0.05 | C42: =IFERROR(B33*B42,"") -> 1800
A43: 9 | B43: =IFERROR(HLOOKUP(B34,'Payout Schedule'!$B$1:$M$13,A43+1,0),"") -> 0.04 | C43: =IFERROR(B33*B43,"") -> 1440
A44: 10 | B44: =IFERROR(HLOOKUP(B34,'Payout Schedule'!$B$1:$M$13,A44+1,0),"") -> 0.04 | C44: =IFERROR(B33*B44,"") -> 1440
A45: 11 | B45: =IFERROR(HLOOKUP(B34,'Payout Schedule'!$B$1:$M$13,A45+1,0),"") -> 0.03 | C45: =IFERROR(B33*B45,"") -> 1080
A46: 12 | B46: =IFERROR(HLOOKUP(B34,'Payout Schedule'!$B$1:$M$13,A46+1,0),"") -> 0.03 | C46: =IFERROR(B33*B46,"") -> 1080
A48: Total | B48: =SUM(B35:B46) -> 1 | C48: =SUM(C35:C46) -> 36000
B50: CHARLIE TEAM
B51: =IF(D12=1,0,IF(D12=2,0,IF(D12=3,E12,IF(D12=4,E12,IF(D12=5,E12,IF(D12=6,E12,IF(D12=7,E12,IF(D12=8,E12,IF(D12=9,E12,IF(D12=10,E12)))))))))) -> 16000 | C51: Payout
A52: Placings | B52: 271-300
A53: 1 | B53: =IFERROR(HLOOKUP(B52,'Payout Schedule'!$B$1:$M$13,A53+1,0),"") -> 0.22 | C53: =IFERROR(B51*B53,"") -> 3520
A54: 2 | B54: =IFERROR(HLOOKUP(B52,'Payout Schedule'!$B$1:$M$13,A54+1,0),"") -> 0.17 | C54: =IFERROR(B51*B54,"") -> 2720
A55: 3 | B55: =IFERROR(HLOOKUP(B52,'Payout Schedule'!$B$1:$M$13,A55+1,0),"") -> 0.12 | C55: =IFERROR(B51*B55,"") -> 1920
A56: 4 | B56: =IFERROR(HLOOKUP(B52,'Payout Schedule'!$B$1:$M$13,A56+1,0),"") -> 0.09 | C56: =IFERROR(B51*B56,"") -> 1440
A57: 5 | B57: =IFERROR(HLOOKUP(B52,'Payout Schedule'!$B$1:$M$13,A57+1,0),"") -> 0.08 | C57: =IFERROR(B51*B57,"") -> 1280
A58: 6 | B58: =IFERROR(HLOOKUP(B52,'Payout Schedule'!$B$1:$M$13,A58+1,0),"") -> 0.07 | C58: =IFERROR(B51*B58,"") -> 1120
A59: 7 | B59: =IFERROR(HLOOKUP(B52,'Payout Schedule'!$B$1:$M$13,A59+1,0),"") -> 0.06 | C59: =IFERROR(B51*B59,"") -> 960
A60: 8 | B60: =IFERROR(HLOOKUP(B52,'Payout Schedule'!$B$1:$M$13,A60+1,0),"") -> 0.05 | C60: =IFERROR(B51*B60,"") -> 800
A61: 9 | B61: =IFERROR(HLOOKUP(B52,'Payout Schedule'!$B$1:$M$13,A61+1,0),"") -> 0.04 | C61: =IFERROR(B51*B61,"") -> 640
A62: 10 | B62: =IFERROR(HLOOKUP(B52,'Payout Schedule'!$B$1:$M$13,A62+1,0),"") -> 0.04 | C62: =IFERROR(B51*B62,"") -> 640
A63: 11 | B63: =IFERROR(HLOOKUP(B52,'Payout Schedule'!$B$1:$M$13,A63+1,0),"") -> 0.03 | C63: =IFERROR(B51*B63,"") -> 480
A64: 12 | B64: =IFERROR(HLOOKUP(B52,'Payout Schedule'!$B$1:$M$13,A64+1,0),"") -> 0.03 | C64: =IFERROR(B51*B64,"") -> 480
A66: Total | B66: =SUM(B53:B64) -> 1 | C66: =SUM(C53:C64) -> 16000
B68: DELTA TEAM
B69: =IF(D12=1,0,IF(D12=2,0,IF(D12=3,0,IF(D12=4,E12,IF(D12=5,E12,IF(D12=6,E12,IF(D12=7,E12,IF(D12=8,E12,IF(D12=9,E12,IF(D12=10,E12)))))))))) -> 16000 | C69: Payout
A70: Placings | B70: 271-300
A71: 1 | B71: =IFERROR(HLOOKUP(B70,'Payout Schedule'!$B$1:$M$13,A71+1,0),"") -> 0.22 | C71: =IFERROR(B69*B71,"") -> 3520
A72: 2 | B72: =IFERROR(HLOOKUP(B70,'Payout Schedule'!$B$1:$M$13,A72+1,0),"") -> 0.17 | C72: =IFERROR(B69*B72,"") -> 2720
A73: 3 | B73: =IFERROR(HLOOKUP(B70,'Payout Schedule'!$B$1:$M$13,A73+1,0),"") -> 0.12 | C73: =IFERROR(B69*B73,"") -> 1920
A74: 4 | B74: =IFERROR(HLOOKUP(B70,'Payout Schedule'!$B$1:$M$13,A74+1,0),"") -> 0.09 | C74: =IFERROR(B69*B74,"") -> 1440
A75: 5 | B75: =IFERROR(HLOOKUP(B70,'Payout Schedule'!$B$1:$M$13,A75+1,0),"") -> 0.08 | C75: =IFERROR(B69*B75,"") -> 1280
A76: 6 | B76: =IFERROR(HLOOKUP(B70,'Payout Schedule'!$B$1:$M$13,A76+1,0),"") -> 0.07 | C76: =IFERROR(B69*B76,"") -> 1120
A77: 7 | B77: =IFERROR(HLOOKUP(B70,'Payout Schedule'!$B$1:$M$13,A77+1,0),"") -> 0.06 | C77: =IFERROR(B69*B77,"") -> 960
A78: 8 | B78: =IFERROR(HLOOKUP(B70,'Payout Schedule'!$B$1:$M$13,A78+1,0),"") -> 0.05 | C78: =IFERROR(B69*B78,"") -> 800
A79: 9 | B79: =IFERROR(HLOOKUP(B70,'Payout Schedule'!$B$1:$M$13,A79+1,0),"") -> 0.04 | C79: =IFERROR(B69*B79,"") -> 640
A80: 10 | B80: =IFERROR(HLOOKUP(B70,'Payout Schedule'!$B$1:$M$13,A80+1,0),"") -> 0.04 | C80: =IFERROR(B69*B80,"") -> 640
A81: 11 | B81: =IFERROR(HLOOKUP(B70,'Payout Schedule'!$B$1:$M$13,A81+1,0),"") -> 0.03 | C81: =IFERROR(B69*B81,"") -> 480
A82: 12 | B82: =IFERROR(HLOOKUP(B70,'Payout Schedule'!$B$1:$M$13,A82+1,0),"") -> 0.03 | C82: =IFERROR(B69*B82,"") -> 480
A84: Total | B84: =SUM(B71:B82) -> 1 | C84: =SUM(C71:C82) -> 16000
B86: ECHO TEAM
B87: =IF(D12=1,0,IF(D12=2,0,IF(D12=3,0,IF(D12=4,0,IF(D12=5,E12,IF(D12=6,E12,IF(D12=7,E12,IF(D12=8,E12,IF(D12=9,E12,IF(D12=10,E12)))))))))) -> 16000 | C87: Payout
A88: Placings | B88: 271-300
A89: 1 | B89: =IFERROR(HLOOKUP(B88,'Payout Schedule'!$B$1:$M$13,A89+1,0),"") -> 0.22 | C89: =IFERROR(B87*B89,"") -> 3520
A90: 2 | B90: =IFERROR(HLOOKUP(B88,'Payout Schedule'!$B$1:$M$13,A90+1,0),"") -> 0.17 | C90: =IFERROR(B87*B90,"") -> 2720
A91: 3 | B91: =IFERROR(HLOOKUP(B88,'Payout Schedule'!$B$1:$M$13,A91+1,0),"") -> 0.12 | C91: =IFERROR(B87*B91,"") -> 1920
A92: 4 | B92: =IFERROR(HLOOKUP(B88,'Payout Schedule'!$B$1:$M$13,A92+1,0),"") -> 0.09 | C92: =IFERROR(B87*B92,"") -> 1440
A93: 5 | B93: =IFERROR(HLOOKUP(B88,'Payout Schedule'!$B$1:$M$13,A93+1,0),"") -> 0.08 | C93: =IFERROR(B87*B93,"") -> 1280
A94: 6 | B94: =IFERROR(HLOOKUP(B88,'Payout Schedule'!$B$1:$M$13,A94+1,0),"") -> 0.07 | C94: =IFERROR(B87*B94,"") -> 1120
A95: 7 | B95: =IFERROR(HLOOKUP(B88,'Payout Schedule'!$B$1:$M$13,A95+1,0),"") -> 0.06 | C95: =IFERROR(B87*B95,"") -> 960
A96: 8 | B96: =IFERROR(HLOOKUP(B88,'Payout Schedule'!$B$1:$M$13,A96+1,0),"") -> 0.05 | C96: =IFERROR(B87*B96,"") -> 800
A97: 9 | B97: =IFERROR(HLOOKUP(B88,'Payout Schedule'!$B$1:$M$13,A97+1,0),"") -> 0.04 | C97: =IFERROR(B87*B97,"") -> 640
A98: 10 | B98: =IFERROR(HLOOKUP(B88,'Payout Schedule'!$B$1:$M$13,A98+1,0),"") -> 0.04 | C98: =IFERROR(B87*B98,"") -> 640
A99: 11 | B99: =IFERROR(HLOOKUP(B88,'Payout Schedule'!$B$1:$M$13,A99+1,0),"") -> 0.03 | C99: =IFERROR(B87*B99,"") -> 480
A100: 12 | B100: =IFERROR(HLOOKUP(B88,'Payout Schedule'!$B$1:$M$13,A100+1,0),"") -> 0.03 | C100: =IFERROR(B87*B100,"") -> 480
A102: Total | B102: =SUM(B89:B100) -> 1 | C102: =SUM(C89:C100) -> 16000
B105: TEAM 6
B106: =IF(D12=1,0,IF(D12=2,0,IF(D12=3,0,IF(D12=4,0,IF(D12=5,0,IF(D12=6,E12,IF(D12=7,E12,IF(D12=8,E12,IF(D12=9,E12,IF(D12=10,E12)))))))))) -> 16000 | C106: Payout
A107: Placings | B107: 271-300
A108: 1 | B108: =IFERROR(HLOOKUP(B107,'Payout Schedule'!$B$1:$M$13,A108+1,0),"") -> 0.22 | C108: =IFERROR(B106*B108,"") -> 3520
A109: 2 | B109: =IFERROR(HLOOKUP(B107,'Payout Schedule'!$B$1:$M$13,A109+1,0),"") -> 0.17 | C109: =IFERROR(B106*B109,"") -> 2720
A110: 3 | B110: =IFERROR(HLOOKUP(B107,'Payout Schedule'!$B$1:$M$13,A110+1,0),"") -> 0.12 | C110: =IFERROR(B106*B110,"") -> 1920
A111: 4 | B111: =IFERROR(HLOOKUP(B107,'Payout Schedule'!$B$1:$M$13,A111+1,0),"") -> 0.09 | C111: =IFERROR(B106*B111,"") -> 1440
A112: 5 | B112: =IFERROR(HLOOKUP(B107,'Payout Schedule'!$B$1:$M$13,A112+1,0),"") -> 0.08 | C112: =IFERROR(B106*B112,"") -> 1280
A113: 6 | B113: =IFERROR(HLOOKUP(B107,'Payout Schedule'!$B$1:$M$13,A113+1,0),"") -> 0.07 | C113: =IFERROR(B106*B113,"") -> 1120
...

Sheet PR National Championships
A1: 5K | B1: 10k | C1: 1/2M | D1: M | E1: 100M | F1: Total
A2: 200000 | B2: 200000 | C2: 200000 | D2: 200000 | E2: 200000 | F2: =sum(A2:E2) -> 1000000

Sheet PR_PROMOTER
A1: Promoter Revenue
A2: Guranteed Sponsorship | B2: ='Master Calculator'!G14 -> 0
A3: Total Entry Income | B3: ='Master Calculator'!I10 -> 3600
A5: Entry to Promoter | B5: ='Master Calculator'!I17 -> 3600
A6: Membership Rebate | B6: ='Master Calculator'!I22 -> 0
A8: Total Promoter Revenue | B8: =sum(B5:B6) -> 3600

Sheet Payout Schedule
A1: # of Entrants | B1: <10 | C1: 11 to 20 | D1: 21-40 | E1: 41-60 | F1: 61-90 | G1: 91-120 | H1: 121-150 | I1: 151-180 | J1: 181-210 | K1: 211-240 | L1: 241-270 | M1: 271-300
A2: 1st | B2: 1 | C2: 0.6 | D2: 0.5 | E2: 0.4 | F2: 0.35 | G2: 0.33 | H2: 0.3 | I2: 0.28 | J2: 0.26 | K2: 0.24 | L2: 0.23 | M2: 0.22
A3: 2nd | C3: 0.4 | D3: 0.3 | E3: 0.3 | F3: 0.25 | G3: 0.23 | H3: 0.21 | I3: 0.19 | J3: 0.18 | K3: 0.18 | L3: 0.17 | M3: 0.17
A4: 3rd | D4: 0.2 | E4: 0.2 | F4: 0.19 | G4: 0.17 | H4: 0.16 | I4: 0.15 | J4: 0.14 | K4: 0.13 | L4: 0.12 | M4: 0.12
A5: 4th | E5: 0.1 | F5: 0.14 | G5: 0.12 | H5: 0.12 | I5: 0.11 | J5: 0.11 | K5: 0.11 | L5: 0.1 | M5: 0.09
A6: 5th | F6: 0.07 | G6: 0.09 | H6: 0.09 | I6: 0.09 | J6: 0.09 | K6: 0.09 | L6: 0.09 | M6: 0.08
A7: 6th | G7: 0.06 | H7: 0.07 | I7: 0.08 | J7: 0.07 | K7: 0.07 | L7: 0.08 | M7: 0.07
A8: 7th | H8: 0.05 | I8: 0.06 | J8: 0.06 | K8: 0.06 | L8: 0.06 | M8: 0.06
A9: 8th | I9: 0.04 | J9: 0.05 | K9: 0.05 | L9: 0.05 | M9: 0.05
A10: 9th | J10: 0.04 | K10: 0.04 | L10: 0.04 | M10: 0.04
A11: 10th | K11: 0.03 | L11: 0.03 | M11: 0.04
A12: 11th | L12: 0.03 | M12: 0.03
A13: 12th | M13: 0.03
B20: =SUM(B2:B19) -> 1 | C20: =SUM(C2:C19) -> 1 | D20: =SUM(D2:D19) -> 1 | E20: =SUM(E2:E19) -> 1 | F20: =SUM(F2:F19) -> 1 | G20: =SUM(G2:G19) -> 1 | H20: =SUM(H2:H19) -> 1 | I20: =SUM(I2:I19) -> 1 | ... M20: =SUM(M2:M19) -> 1

Sheet Notes
A1: Name | B1: Definition
A2: "D" | B2: D1, D2,D3 etc..simply stands for a "Division" or a split in the contestents. This does not refere to anything mathmatical, just a reference to way to split up the total number of contestents
A4: D1 | B4: The first split of contestents. This is the top or open division/the best of the contestents.
A5: D1-Added Money | B5: Added money that comes from the over contestent pot. This is not TRUE added money, this comes from the existing contestents pot
A6: True Added Money | B6: This is money from sponsors or outside of entry fees that is added to the contestent payouts
A7: D2 | B7: The seceond contestent division
A8: D3 | B8: Third contestent division
A9: D4 | B9: 4th contestent division
A10: D5 | B10: 5th contestent division
A11: Contestent Divisions | B11: This variable will determine how many "D"s will be in the race. These can only range from 1-5
A12: Division payout | B12: This is equal to the total contestent payout divided by the number of divisions
A14: D payouts | B14: A drop down
